daixm_mns-1.1.5.data/scripts/mnscmd
daixm_mns-1.1.5.dist-info/DESCRIPTION.rst
daixm_mns-1.1.5.dist-info/METADATA
daixm_mns-1.1.5.dist-info/RECORD
daixm_mns-1.1.5.dist-info/WHEEL
daixm_mns-1.1.5.dist-info/metadata.json
daixm_mns-1.1.5.dist-info/top_level.txt
mns/__init__.py
mns/account.py
mns/mns_client.py
mns/mns_common.py
mns/mns_exception.py
mns/mns_http.py
mns/mns_request.py
mns/mns_tool.py
mns/mns_xml_handler.py
mns/pkg_info.py
mns/queue.py
mns/subscription.py
mns/topic.py
