Metadata-Version: 2.0
Name: daixm-mns
Version: 1.1.5
Summary: Aliyun Message Service Library
Home-page: UNKNOWN
Author: Aliyun MNS
Author-email: UNKNOWN
License: MIT
Platform: UNKNOWN
